LICENSE.md
README.md
setup.py
zegami_sdk/__init__.py
zegami_sdk/_annotation_methods.py
zegami_sdk/annotation.py
zegami_sdk/client.py
zegami_sdk/collection.py
zegami_sdk/helper.py
zegami_sdk/nodes.py
zegami_sdk/source.py
zegami_sdk/stats.py
zegami_sdk/test.py
zegami_sdk/util.py
zegami_sdk/workspace.py
zegami_sdk_testrelease.egg-info/PKG-INFO
zegami_sdk_testrelease.egg-info/SOURCES.txt
zegami_sdk_testrelease.egg-info/dependency_links.txt
zegami_sdk_testrelease.egg-info/requires.txt
zegami_sdk_testrelease.egg-info/top_level.txt