Metadata-Version: 2.1
Name: zegami-sdk-testrelease
Version: 0.4.6
Summary: A suite of tools for interacting with Zegami through Python.
Home-page: https://github.com/zegami/zegami-python-sdk
Author: Zegami Ltd
Author-email: help@zegami.com
License: Apache 2.0
Platform: UNKNOWN
Requires-Python: >=3.6
License-File: LICENSE.md
